ykenan_file/__init__.py
ykenan_file/_create_.py
ykenan_file/_read_.py
ykenan_file/_static_method_.py
ykenan_file/_thread_file_.py
ykenan_file/_util_.py
ykenan_file-0.2.8.dist-info/METADATA
ykenan_file-0.2.8.dist-info/WHEEL
ykenan_file-0.2.8.dist-info/licenses/LICENSE
ykenan_file-0.2.8.dist-info/RECORD
